norma/__init__.py
norma/joint_normal.py
norma/tests/__init__.py
norma/tests/joint_normal_tests.py
norma-0.1.1.dist-info/DESCRIPTION.rst
norma-0.1.1.dist-info/METADATA
norma-0.1.1.dist-info/RECORD
norma-0.1.1.dist-info/WHEEL
norma-0.1.1.dist-info/metadata.json
norma-0.1.1.dist-info/top_level.txt
