Metadata-Version: 2.0
Name: norma
Version: 0.1.1
Summary: UNKNOWN
Home-page: https://github.com/robdmc/norma.git
Author: Rob deCarvalho
Author-email: unlisted@unlisted.net
License: MIT
Platform: UNKNOWN
Classifier: Programming Language :: Python :: 2.7
Classifier: Programming Language :: Python :: 3.4
Classifier: Programming Language :: Python :: 3.5
Classifier: Intended Audience :: Developers
Classifier: License :: OSI Approved :: MIT License
Classifier: Operating System :: OS Independent
Requires-Dist: pandas
Requires-Dist: scipy
Provides-Extra: dev
Requires-Dist: Sphinx; extra == 'dev'
Requires-Dist: coverage; extra == 'dev'
Requires-Dist: flake8; extra == 'dev'
Requires-Dist: mock; extra == 'dev'
Requires-Dist: nose; extra == 'dev'
Requires-Dist: sphinx-rtd-theme; extra == 'dev'
Requires-Dist: wheel; extra == 'dev'
